{"hash":"b019132cdf18eb9f78219b0565b919b16f679c3f","data":{"doc":{"id":"1e0ce42ca507e44418b689f2fb4b4cdf","title":"Commencer","description":"","contributors":["Vourhey","positivecrash"],"headings":[],"subtitles":[{"depth":2,"value":"Qu'est-ce que Robonomics","anchor":"#quest-ce-que-robonomics"},{"depth":2,"value":"Démarrage rapide du réseau Robonomics","anchor":"#démarrage-rapide-du-réseau-robonomics"},{"depth":3,"value":"Avantages pour les diplômés de Robonomics Academy","anchor":"#avantages-pour-les-diplômés-de-robonomics-academy"},{"depth":2,"value":"Contenu de la documentation","anchor":"#contenu-de-la-documentation"},{"depth":3,"value":"Je suis un développeur de Dapp","anchor":"#je-suis-un-développeur-de-dapp"},{"depth":3,"value":"Je suis un ingénieur en robotique","anchor":"#je-suis-un-ingénieur-en-robotique"}],"content":"\n## Qu'est-ce que Robonomics\n\nLa plateforme Robonomics fournit des outils pour travailler avec le réseau économique des robots. Robonomics permet aux concepteurs de villes intelligentes et de zones industrielles 4.0 de créer de la confiance parmi les [services de robots autonomes](/docs/glossary#cyber-physical-system), de fournir un [accès direct aux utilisateurs via dapp](/docs/glossary#dapp) pour commander des produits auprès d'usines autonomes et de services de réseaux de capteurs urbains. Cela permettra à son tour de mettre en place un système décentralisé qui surveille globalement les activités des systèmes cyber-physiques.\n\nLe graphique suivant décrit la place qu'occupe Robonomics dans le scénario:\n\n<robo-wiki-picture src=\"robonomics_network_basic_scheme.jpg\" alt=\"Robonomics Network scenario\" />\n\n<!-- ![Robonomics Chart](../images/robonomics_network_basic_scheme.jpg \"Robonomics Network scenario\") -->\n\nTrouvez plus d'informations dans [Building dApps on Robonomics deck](https://gateway.pinata.cloud/ipfs/QmNNdLG3vuTsJtZtNByWaDTKRYPcBZSZcsJ1FY6rTYCixQ/Robonomics_keypoint_March_2021.pdf)\n\n## Démarrage rapide du réseau Robonomics\n**Pour faciliter l'intégration des nouveaux venus, les développeurs principaux de Robonomics ont mis au point une [courbe d'apprentissage en 6 leçons](/docs/wschool2021-intro/)!**\n\nVous explorerez l'architecture IoT sans serveur ! Robonomics Web Services (RWS) est le service infrastructurel de base pour la robotique et l'IoT sur Polkadot && IPFS.\n\nLes diplômés du cours peuvent lancer une chaîne de relais locale et contrôler un appareil compatible ROS grâce à une transaction inter-chaînes.\n\n**[Rejoignez Robonomics Developers Discord](https://discord.gg/jTxqGeF5Qy) pour vous connecter à la communauté et obtenir un support technique.**\n\n### Avantages pour les diplômés de Robonomics Academy\n- Stage pour les meilleurs étudiants   Devenez membre de l'équipe Robonomics et contribuez au développement du produit choisi.\n- Communauté active && événements réguliers   Faites partie de la communauté d'apprenants, discutez de vos cas d'utilisation avec des experts de l'industrie. Faites équipe et participez à des hackathons !\n- Certificat de fin de formation   Ajoutez un certificat de fin de cours sur la création de DAPPs pour l'IoT à votre portfolio.\n- Aide à l'admission à l'université ITMO. Que vous soyez en licence ou en master, vous bénéficierez d'une assistance pour votre admission à l'université.\n- Opportunités de financement && d'accélération : 1)Demandez une subvention de soutien Academia pouvant aller jusqu'à 50 000 $ ; 2)Participez au programme d'accélération Robonomics builders soutenu par la Web3 Foundation ; 3)Déployez votre DAPP autonome sur Robonomics ; 4)Monétisez-le && bénéficiez du soutien marketing de l'équipe Robonomics.\n\n\n## Contenu de la documentation\n\n### Je suis un développeur de Dapp\n\n- [Robonomics-js sur GitHub](https://github.com/airalab/robonomics-js) - simple SDK Javascript pour les développeurs d'applications Robonomics Network.\n- [Modèle de Dapp](https://github.com/airalab/vue-dapp-robonomics-template) - utilise Vue.js\n- [Documentation Wiki](/docs/robonomics-js/)\n\n### Je suis un ingénieur en robotique\n\nConsultez la section [cas](/docs/iot-sensors-connectivity/) et commencez à développer grâce aux [exemples](/docs/agent-development-examples).\n\n","tools":[],"fileInfo":{"path":"fr/getting-started.md","name":"getting-started"}}},"context":{}}