{"hash":"1c69c8a2260ab21fb37b665d9cfdf0730a5c4d9c","data":{"doc":{"id":"77a7c52c3eb693830ef4f14115c2e825","title":"Lightsout Factory","description":"","contributors":["ValanisZz","GiggleSeagull","Valiento"],"translated":true,"headings":[],"subtitles":[{"depth":2,"value":"Project goal","anchor":"#project-goal"},{"depth":2,"value":"Requirements","anchor":"#requirements"},{"depth":2,"value":"Legend","anchor":"#legend"},{"depth":2,"value":"Rules","anchor":"#rules"}],"content":"\n![Lightsout Factory Preview](../images/lightsout-factory/factory_preview_numbers.jpg)\n\n## Project goal\nProvide optimized and fully automated factory manufacturing depending on the specified requirements\n\n## Requirements\n- FischerTechink factory\n- Siemens PLC S7-1200\n- 6 additional PLC blocks (SM-1223)\n- LattePanda with [Ubuntu 20.04](https://releases.ubuntu.com/20.04/) and [ROS Noetic](http://wiki.ros.org/noetic/Installation) installed\n- [modbus](https://github.com/HumaRobotics/modbus)\n\n## Legend\n| Block number |           Description           | Amount, pcs |\n|--------------|---------------------------------|-------------|\n|     0.x      | Warehouse                       |      2      |\n|      1       | Simple conveyor                 |      8      |\n|      2       | Rotary conveyor                 |      2      |\n|     3.1      | Arrival conveyor                |      4      |\n|     3.2      | Departure conveyor              |      1      |\n|     4.x      | Handler                         |      4      |\n|     5.x      | Loader                          |      2      |\n|      6       | Color Recognition Block         |      1      |\n\n## Rules\n- Factory movement is organised from right to left side\n- Right side stands for 0, left side stands for 1\n- All handlers (4.x) are just models of various processing machines\n- Each block has a tactile or light sensor (except of warehouse storage positioning)\n\n"}},"context":{}}