{"hash":"469d33cce4695fb6d977e85fa99778d018d4e3f8","data":{"doc":{"id":"f181f28f3ec5920cdb3001ccef3fd75d","title":"AIRA Installation","description":"","contributors":["akru"],"translated":true,"headings":[],"subtitles":[],"content":"\n- [**How to launch AIRA on VirtualBox**](/docs/aira-installation-on-vb/)\n\n- **The installation on Raspberry Pi** is as simple as writing an image of AIRA on SD card using `dd` or [Etcher](https://www.balena.io/etcher/), for example.\n\n\n","tools":[],"fileInfo":{"path":"en/aira-installation.md","name":"aira-installation"}}},"context":{}}