{"hash":"f0c4f9a9cb5ad2f8ccd3358031883a3caf6ee289","data":{"doc":{"id":"86dee1fec959759bcceeeb25dd234963","title":"Réseau de capteurs décentralisé","description":"","contributors":["LoSk-p"],"headings":[],"subtitles":[],"content":"\nLes articles sur le réseau de capteurs décentralisés ont été transférés à Robonomics Academy: https://robonomics.academy/fr/cours-en-ligne/cours-de-connectivite-des-capteurs/","tools":[],"fileInfo":{"path":"fr/sensors-network-introduction.md","name":"sensors-network-introduction"}}},"context":{}}