{"hash":"500ba57b52b36c997c1da8af71e424ba35d5fc3f","data":{"doc":{"id":"c849d25dcdfa753f7da1af2eba2c8c1e","title":"Deployment of Feecc Analytics","description":"","contributors":["timofeev41"],"headings":[],"subtitles":[{"depth":2,"value":"Analytics backend startup","anchor":"#analytics-backend-startup"},{"depth":3,"value":"Clone source code","anchor":"#clone-source-code"},{"depth":3,"value":"Configuration","anchor":"#configuration"},{"depth":3,"value":"Application startup","anchor":"#application-startup"},{"depth":3,"value":"Check deployment","anchor":"#check-deployment"},{"depth":2,"value":"Analytics frontend startup","anchor":"#analytics-frontend-startup"},{"depth":3,"value":"Clone source code","anchor":"#clone-source-code-1"},{"depth":3,"value":"Configuration","anchor":"#configuration-1"},{"depth":3,"value":"Application startup","anchor":"#application-startup-1"},{"depth":3,"value":"Check deployment","anchor":"#check-deployment-1"}],"content":"\nIn this guide, we will talk about the deployment of Feecc Analytics.\n\nYou will need `git` and `docker-compose` (v3 or higher) installed in order to run\n\n## Analytics backend startup\n\n### Clone source code\n\nRun:\n\n```\ngit clone https://github.com/Multi-Agent-io/feecc-analytics-backend\n```\n\nTo access dev version (beta) change branch to `development`\n\n### Configuration\n\nEdit your `.env` file with any text editor.\n\n`.env` options:\n\n* `MONGO_CONNECTION_URL` - URL MongoDB (in form of `mongodb://<username:password>@<host>:<port>/<defaultauthdb>`)\n\n* `MONGO_DATABASE_NAME` - name of mongodb database which will be used for reading/writing data\n\n* `SECRET_KEY` - secret key for hash/dehash\n\n* `IPFS_GATEWAY_HOST` - URL of IPFS Gateway\n\n* `USE_DATALOG` - Will analytics send data to Robonomics Datalog (True/False)\n\n* `ROBONOMICS_SEED` - Seed-phrase of the Robonomics wallet on the **Kusama** network\n\n### Application startup\n\nRun `docker-compose up --build` to start an application\n\nIf some parameters were not filled (or filled incorrectly) the system will generate an error, in this case check the\ncorrectness of filling the `.env`\n\n### Check deployment\n\nTo check startup, go to `localhost:5002/docs`.\n\nIf all done correctly, you will see a page (generated by Swagger) with all Feecc Analytics REST API endpoints. Now you\nare ready to launch the frontend.\n\n## Analytics frontend startup\n\n### Clone source code\n\nRun:\n\n```\ngit clone https://github.com/Multi-Agent-io/feecc-analytics-frontend\n```\n\nTo access dev version (beta) change branch to `dev`\n\n### Configuration\n\nEdit `src/config.json` file with any text editor\n\nOptions:\n\n* `base_url` - URL of Feecc Analytics Backend (in form of `хх.хх.хх.хх:port`)\n\n### Application startup\n\nTo start run:\n\n```\ndocker-compose up --build\n```\n\n### Check deployment\n\nTo check if it works, go to `localhost:8081/docs`.\n","tools":["Feecc Analytics frontend https://github.com/Multi-Agent-io/feecc-analytics-frontend","Feecc Analytics backend https://github.com/Multi-Agent-io/feecc-analytics-backend"],"fileInfo":{"path":"feecc-system-deploy-feecc-analytics.md","name":"feecc-system-deploy-feecc-analytics"}}},"context":{}}